{
    "canonical_name": "control-1950", 
    "description": "Historical to near future coupled ocean atmosphere simulations (1950-2050) with fixed 1950s forcing at high and standard resolution.\nFor optimal comparison between models aerosol concentrations would be preferable and not emissions.\nAt least one ensemble member at high resolution, minimum atmosphere 25-50 km at mid-latitudes and ocean resolution of 0.25 degrees, and a minimum of daily coupling between ocean and atmosphere.\nAt least one ensemble member at standard model resolution.", 
    "keywords": "HighResMIP, Tier 2, coupled, 1950s", 
    "long_name": "coupled control with fixed 1950's forcing (HighResMIP equivalent of pre-industrial control)", 
    "mip_era": "cmip6", 
    "rationale": "Control simulations.", 
    "related_experiments": [
        "future-SSP245", 
        "future-SSP370", 
        "future-SSP585", 
        "hist-1950"
    ], 
    "requirements": [
        {
            "canonical_name": "1950-2049 100yrs", 
            "description": "Historical Scenario, from recent past to near future.", 
            "isConformanceRequested": false, 
            "keywords": "1950, 2049, Historical, Scenario, Recent Past, Near Future", 
            "label": "1950-2049 100yrs", 
            "type": "temporal-constraint"
        }, 
        {
            "canonical_name": "1950 WMGHG Concentrations", 
            "description": "1950 Forcing data for concentration-driven historical CMIP6 runs. Here, we provide an outline of a consolidated set of atmospheric concentrations for the long-lived greenhouse-gases, including CO2, CH4, N2O, HFCs, PFCs, SF6, several ODS, and NF3 to serve as input for the CMIP6 Historical simulations. \nDepending on the model setup and emission species (short-lived, ozone, long-lived GHG), the historical simulation is driven by emissions and/or concentrations.", 
            "isConformanceRequested": true, 
            "keywords": "Historical, Well Mixed Greenhouse Gas, WMGHG, 1950", 
            "label": "1950 WMGHG Concentrations", 
            "type": "forcing-constraint"
        }, 
        {
            "canonical_name": "1950 Land Use", 
            "description": "1950 global gridded land-use forcing datasets.  This new generation of \u201cland use harmonization\u201d (LUH2) builds upon past work from CMIP5, and includes updated inputs, higher spatial resolution, more detailed land-use transitions, and the addition of important agricultural management layers.", 
            "isConformanceRequested": true, 
            "keywords": "Historical, land use, 1950", 
            "label": "1950 Land Use", 
            "type": "forcing-constraint"
        }, 
        {
            "canonical_name": "1950 Stratospheric Aerosol", 
            "description": "1950 stratospheric aerosol", 
            "isConformanceRequested": true, 
            "keywords": "historical, stratospheric, aerosol, 1950", 
            "label": "1950 Stratospheric Aerosol", 
            "type": "forcing-constraint"
        }, 
        {
            "canonical_name": "1950 Aerosol Forcing", 
            "description": "Mass mixing ratio fields at 1x1 degree resolution for 1950 main aerosol components (sulphate, black carbon, organic carbon, nitrate, sea salt, mineral dust),  along with effective radius per species.", 
            "isConformanceRequested": true, 
            "keywords": "1950, aerosol, forcing, CMIP6", 
            "label": "1950 Aerosol Forcing", 
            "type": "forcing-constraint"
        }, 
        {
            "canonical_name": "1950 Emissions", 
            "description": "Core emissions datasets for 1950.", 
            "isConformanceRequested": true, 
            "keywords": "1950, emissions", 
            "label": "1950 Emissions", 
            "type": "forcing-constraint"
        }, 
        {
            "canonical_name": "1950 Solar Forcing", 
            "description": "1950 solar forcing of the Earth system consistent with historical observations.", 
            "isConformanceRequested": true, 
            "keywords": "1950, Solar, Forcing, SSI, TSI, Proton Forcing, Electron Forcing", 
            "label": "1950 Solar Forcing", 
            "type": "forcing-constraint"
        }, 
        {
            "canonical_name": "1950 O3 and Stratospheric H2O Concentrations", 
            "description": "1950 ozone concentration data encompassing both the stratosphere and the troposphere and a stratospheric water vapour concentration data.", 
            "isConformanceRequested": true, 
            "keywords": "1950, stratospheric, ozone, water vapour, O3, H2O, concentration", 
            "label": "1950 O3 and Stratospheric H2O Concentrations", 
            "type": "forcing-constraint"
        }, 
        {
            "canonical_name": "HighAndStandardResolution", 
            "description": "At least two simulations, one at high resolution (minimum 25-50 km at mid-latitudes), and one at the standard model resolution", 
            "isConformanceRequested": false, 
            "keywords": "high resolution, standard resolution, at least two members", 
            "label": "HighAndStandardResolution", 
            "type": "ensemble"
        }, 
        {
            "canonical_name": "AOGCM/ESM Configuration", 
            "description": "Use a coupled Atmosphere-Ocean general circulation model or an Earth System Model", 
            "isConformanceRequested": false, 
            "keywords": "AOGCM, ESM, Atmosphere-Ocean, Earth System, Model, Configuration", 
            "label": "AOGCM/ESM Configuration", 
            "type": "model-configuration"
        }, 
        {
            "canonical_name": "HighResAtmos", 
            "description": "25-50km minimum resolution at mid-latitudes", 
            "isConformanceRequested": false, 
            "keywords": "High Resolution, 25-50 km,", 
            "label": "HighResAtmos", 
            "type": "model-configuration"
        }, 
        {
            "canonical_name": "HighResOcean", 
            "description": "Ocean resolution 0.25 degrees", 
            "isConformanceRequested": false, 
            "keywords": "High resolution ocean, 0.25 degrees", 
            "label": "HighResOcean", 
            "type": "model-configuration"
        }, 
        {
            "canonical_name": "standardModelResolution", 
            "description": "standard model resolution", 
            "isConformanceRequested": false, 
            "keywords": "Standard Model Resolution", 
            "label": "standardModelResolution", 
            "type": "model-configuration"
        }, 
        {
            "canonical_name": "DailyCoupling", 
            "description": "Minimum daily coupling between ocean and atmosphere.  Preferably more frequent, 3hr or 1hr.", 
            "isConformanceRequested": false, 
            "keywords": "Daily coupling or more", 
            "label": "DailyCoupling", 
            "type": "model-configuration"
        }
    ], 
    "uid": "866f67b7-6b96-40fb-8fd4-6f99d4d7f3bf", 
    "viewerURL": "http://view.es-doc.org?renderMethod=id&project=cmip6-draft&id=866f67b7-6b96-40fb-8fd4-6f99d4d7f3bf&version=latest&client=mohc"
}