{
    "canonical_name": "piClim-4xCO2", 
    "description": "A single 30-year uncoupled (atmosphere and land) simulation in which sea suface temperature (SST) and sea ice distributions are specified and vegetation may interact.  Carbon Dioxide concentrations set to 4 times Pre-Industrial values, sea ice and other anthropogenic forcing agents are specified at pre-industrial values.", 
    "keywords": "RFMIP, Tier 1, 4xCO2, uncoupled, atmosphere-land", 
    "long_name": "RFMIP 4xCO2 effective radiative forcing", 
    "mip_era": "cmip6", 
    "rationale": "Quantify the effective radiative forcing (ERF) of 4xCO2.", 
    "related_experiments": [
        "abrupt-4xCO2", 
        "piClim-control"
    ], 
    "requirements": [
        {
            "canonical_name": "30yrs", 
            "description": "Run for 30 years, timeslice experiment.", 
            "isConformanceRequested": false, 
            "keywords": "30 years", 
            "label": "30yrs", 
            "type": "temporal-constraint"
        }, 
        {
            "canonical_name": "PIControlSST", 
            "description": "Pre-Industrial sea surface temperature from the piControl experiment", 
            "isConformanceRequested": false, 
            "keywords": "pre-industrial control, SST, sea surface temperature", 
            "label": "PIControlSST", 
            "type": "forcing-constraint"
        }, 
        {
            "canonical_name": "PIControl SIC", 
            "description": "Pre-Industrial sea ice concentration from the piControl experiment.", 
            "isConformanceRequested": false, 
            "keywords": "pre-industrial control, SIC, sea ice, sea ice concentration", 
            "label": "PIControl SIC", 
            "type": "forcing-constraint"
        }, 
        {
            "canonical_name": "Abrupt4xCO2Increase", 
            "description": "Impose an instantaneous quadrupling of atmospheric carbon dioxide concentration, then hold fixed.", 
            "isConformanceRequested": false, 
            "keywords": "4x, CO2, 4xCO2, instant, instantaneous, quadrupling, ipcc, climate, deck", 
            "label": "Abrupt4xCO2Increase", 
            "type": "forcing-constraint"
        }, 
        {
            "canonical_name": "PIForcingExcludingCO2", 
            "description": "Pre-Industrial forcing excluding carbon dioxide (CO2).", 
            "isConformanceRequested": true, 
            "keywords": "Pre-industrial forcing, excluding carbon dioxide, excluding co2", 
            "label": "PIForcingExcludingCO2", 
            "type": "forcing-constraint"
        }, 
        {
            "canonical_name": "SingleMember", 
            "description": "One ensemble member", 
            "isConformanceRequested": false, 
            "keywords": "Single, simulation, run, ensemble", 
            "label": "SingleMember", 
            "type": "ensemble"
        }, 
        {
            "canonical_name": "AtmosLandConfig", 
            "description": "An uncoupled (atmosphere-land) model.", 
            "isConformanceRequested": false, 
            "keywords": "atmosphere-land model configuration", 
            "label": "AtmosLandConfig", 
            "type": "model-configuration"
        }
    ], 
    "uid": "c3480ce8-bfa3-4cdf-a9d4-e8cc28b5b362", 
    "viewerURL": "http://view.es-doc.org?renderMethod=id&project=cmip6-draft&id=c3480ce8-bfa3-4cdf-a9d4-e8cc28b5b362&version=latest&client=mohc"
}