{
    "canonical_name": "piControl-withism", 
    "description": "The pre-industrial control in a model with interactive ice sheet model.   The experiment should be identical to the corresponding standard CMIP AOGCM experiment except for the treatment of ice sheets.\nThe spin up may require the GCM and ISM to be asynchronously coupled until the system reaches quasi-equilibrium.  \nOnce equilibrium is reached, run for multi-hundred years (500 years suggested).", 
    "governing_mips": [
        "ismip6"
    ], 
    "keywords": "ISMIP6, Tier 1, piControl,  interactive ISM, interactive ice sheets", 
    "long_name": "Pre-industrial control with interactive ice sheets", 
    "mip_era": "cmip6", 
    "rationale": "To produce a realistic non-drifting coupled state, and assess systematic model bias.     \nTo capture unforced natural variability.", 
    "related_experiments": [
        {
            "name": "1pctCO2to4x-withism", 
            "relationship": "is_initializer_of"
        }, 
        {
            "name": "historical-withism", 
            "relationship": "is_initializer_of"
        }, 
        {
            "name": "piControl", 
            "relationship": "is_perturbation_from"
        }
    ], 
    "related_mips": [
        "ismip6"
    ], 
    "requirements": [
        {
            "canonical_name": "500yrs", 
            "description": "Run for 500 years.", 
            "isConformanceRequested": false, 
            "keywords": "500 years, control, idealised", 
            "label": "500yrs", 
            "type": "temporal-constraint"
        }, 
        {
            "canonical_name": "Pre-Industrial CO2 Concentration", 
            "description": "Constant pre-industrial Carbon Dioxide (CO2) concentration. The CO2 concentration should be representative of Earth around the year 1850.", 
            "isConformanceRequested": true, 
            "keywords": "Pre-Industrial, CO2, Concentration, 1850", 
            "label": "Pre-Industrial CO2 Concentration", 
            "scope": "mip-era", 
            "type": "forcing-constraint"
        }, 
        {
            "canonical_name": "Pre-Industrial Forcing Excluding CO2", 
            "description": "Pre-Industrial forcing excluding carbon dioxide (CO2).", 
            "isConformanceRequested": true, 
            "keywords": "Pre-industrial forcing, excluding carbon dioxide, excluding co2", 
            "label": "Pre-Industrial Forcing Excluding CO2", 
            "type": "forcing-constraint"
        }, 
        {
            "canonical_name": "Pre-Industrial Solar Particle Forcing", 
            "description": "Pre-Industrial solar particle forcing (1850-1873 mean). For models with interactive stratospheric chemistry.  Proton forcing: HOx and NOx production by solar protons. Electron forcing:  Kp- or Ap-index to describe ionisation from electron precipitation in the lower thermosphere and upper mesosphere. Cosmic ray forcing:  ion-pair production by galactic cosmic rays.  CMIP6 models that do not have interactive chemistry should  prescribe the CMIP6 recommended ozone forcing data set.", 
            "isConformanceRequested": true, 
            "keywords": "Solar forcing, Pre-Industrial, pi, Particle forcing, proton forcing, electron forcing, cosmic ray ionisation", 
            "label": "Pre-Industrial Solar Particle Forcing", 
            "type": "forcing-constraint"
        }, 
        {
            "canonical_name": "SingleMember", 
            "description": "One ensemble member", 
            "isConformanceRequested": false, 
            "keywords": "Single, simulation, run, ensemble", 
            "label": "SingleMember", 
            "type": "ensemble"
        }, 
        {
            "canonical_name": "Initialisation after spin-up", 
            "description": "Initialisation after the system reaches quasi-equilibrium", 
            "isConformanceRequested": false, 
            "keywords": "spin up, initialisation, quasi-equilibrium", 
            "label": "Initialisation after spin-up", 
            "type": "ensemble"
        }, 
        {
            "canonical_name": "AOGCM-ISM Configuration", 
            "description": "Use a coupled Atmosphere-Ocean general circulation model or an Earth System Model with interactive ice sheets", 
            "isConformanceRequested": false, 
            "keywords": "AOGCM-ISM, ESM-ISM, Atmosphere-Ocean-IceSheet, Earth System, Model, Configuration", 
            "label": "AOGCM-ISM Configuration", 
            "type": "model-configuration"
        }
    ], 
    "tier": 1, 
    "uid": "2728afe7-0a40-4616-ab65-f07918c79e29", 
    "viewerURL": "https://documentation.es-doc.org/cmip6/experiments/piControl-withism?client=mohc"
}