{"description": 1.0, "parties": [{"meta": {"type": "cim.2.shared.Responsibility"}, "parties": ["Represents the high end of the range of plausible future forcing pathways.", "point of contact:", "Brian O'Neill"]}], "canonicalName": "RCP85wmGHG", "name": "RCP85 Well Mixed GHG", "citations": [{"meta": {"type": "cim.2.shared.DocReference"}, "type": "cim.2.shared.Citation", "version": 1, "id": "6fa09901-c2c9-4584-b241-0328f8eea873"}, {"meta": {"type": "cim.2.shared.DocReference"}, "type": "cim.2.shared.Citation", "version": 1, "id": "9e139643-3060-4b5b-9869-269f6d66c19b"}], "meta": {"author": {"version": 1, "meta": {"type": "cim.2.shared.DocReference"}, "uid": "253825f3-fbc8-43fb-b1f6-cc575dc693eb"}, "createDate": "2016-07-04 13:00:00", "project": "cmip6-draft", "source": "spreadsheet", "version": 1, "updateDate": "2016-07-04 13:00:00", "type": "cim.2.designing.ForcingConstraint", "id": "4f543291-f4dd-4a26-bd5d-2320c615f2f4"}, "rationale": "Representative Concentration Pathway 8.5, future, 21st century, SSP5, RCP8.5, Well-mixed Greenhouse Gas, CO2", "longName": "Representative Concentration Pathway 8.5 Well Mixed Greenhouse Gases", "keywords": 1.0, "isConformanceRequested": false}