{"additionalRequirements": [{"id": "031e105f-433b-44ee-9569-c8ee816e55f6", "version": 1, "type": "cim.2.designing.ForcingConstraint", "name": "ReducedRCP70sls", "ontologyTypeKey": "cim.2.shared.DocReference"}, {"id": "752ac62d-0910-47cc-bc1d-3a4ff5694d6a", "version": 1, "type": "cim.2.designing.ForcingConstraint", "name": "ReducedRCP70aer", "ontologyTypeKey": "cim.2.shared.DocReference"}, {"id": "91b823e6-886f-4428-8084-bac49fc5fa18", "version": 1, "type": "cim.2.designing.ForcingConstraint", "name": "ReducedRCP70aerpre", "ontologyTypeKey": "cim.2.shared.DocReference"}, {"id": "24a12dc4-9223-4a1b-90ad-0430bfaa99e1", "version": 1, "type": "cim.2.designing.ForcingConstraint", "name": "ReducedRCP70O3pre", "ontologyTypeKey": "cim.2.shared.DocReference"}], "ontologyTypeKey": "cim.2.designing.NumericalRequirement", "parties": [{"party": ["William Collins", "Jean-Fran\u00e7ois Lamarque", "Michael Schulz"], "ontologyTypeKey": "cim.2.shared.Responsibility"}], "canonicalName": "ReducedRCP70NTCF", "name": "ReducedRCP70NTCF", "citations": [{"version": 1, "type": "cim.2.shared.Citation", "id": "9e139643-3060-4b5b-9869-269f6d66c19b", "ontologyTypeKey": "cim.2.shared.DocReference"}], "meta": {"language": "en", "author": {"version": 1, "uid": "253825f3-fbc8-43fb-b1f6-cc575dc693eb", "ontologyTypeKey": "cim.2.shared.DocReference"}, "institute": "--", "createDate": "2016-07-04 13:00:00", "project": "cmip6-draft", "source": "spreadsheet", "version": 1, "updateDate": "2016-07-04 13:00:00", "ontologyTypeKey": "cim.2.shared.DocMetaInfo", "type": "cim.2.designing.NumericalRequirement", "id": "e3ac7cf0-6c67-4092-b9c8-8bc4df2a5e22"}, "longName": "Reduced RCP 7.0 Near Term Climate Forcers", "keywords": "AerChemMIP, Reduced RCP7.0 NTCF, scenario", "isConformanceRequested": false, "description": "Impose changing concentrations of reduced RCP7.0 Near Term Climate Forcers (NTCF). Beginning in 2014 with air quality policies (or maximum feasible reductions) applied to the SSP3-7 NTCF emissions."}