{"responsibleParties": [{"party": [{"id": "4d7c6e45-99f2-4f79-918f-4545120a7ecf", "version": 1, "type": "cim.2.shared.Party", "name": "Davide Zanchettin", "ontologyTypeKey": "cim.2.shared.DocReference"}, {"id": "2630da7c-a5c9-48e5-ab20-a07e28f93798", "version": 1, "type": "cim.2.shared.Party", "name": "Claudia Timmreck", "ontologyTypeKey": "cim.2.shared.DocReference"}], "ontologyTypeKey": "cim.2.shared.Responsibility"}], "requirements": [{"id": "83acd6ca-ef0b-40fc-b2fd-2055ece97b48", "version": 1, "type": "cim.2.designing.TemporalConstraint", "name": "3yrs1850-1852", "ontologyTypeKey": "cim.2.shared.DocReference"}, {"id": "d9d492b2-6bc6-4f28-854f-09aded7d4b42", "version": 1, "type": "cim.2.designing.ForcingConstraint", "name": "pinatuboAerosol", "ontologyTypeKey": "cim.2.shared.DocReference"}, {"id": "3fee4727-ee95-4720-bc59-9ab91eba26ab", "version": 1, "type": "cim.2.designing.NumericalRequirement:forcing_constraint", "name": "piForcingExcludingStratAer", "ontologyTypeKey": "cim.2.shared.DocReference"}, {"id": "e0d24abf-073d-4b68-8000-5a4c6f2519a3", "version": 1, "type": "cim.2.designing.EnsembleRequirement", "name": "25shortInitialisations", "ontologyTypeKey": "cim.2.shared.DocReference"}, {"id": "4cf855cf-777b-4af7-aa47-9fe7466cfce3", "version": 1, "type": "cim.2.designing.NumericalRequirement:model_configuration", "name": "AOGCM/ESMConfiguration", "ontologyTypeKey": "cim.2.shared.DocReference"}], "description": "1991 Pinatubo forcing as used in the CMIP6 historical simulations.  Maintain the same constant boundary forcing as the pre-industrial control integration, except for the volcanic forcing. Requires special diagnostics of parameterised and resolved wave forcings, radiative and latent heating rates. The experiment will not account for the actual climate conditions when the real event ocurred (e.g., presence and strength of additional forcing factors). Instead, the experiment is designed to span very different initial climate states to systematically assess uncertainties in the post-eruption behavior that are related to background climate conditions. Run at least 25 ensemble members for 3 years.", "relatedExperiments": [{"id": "7dd72de5-c5b6-412c-9b4c-540f09538d9a", "version": 1, "type": "cim.2.designing.NumericalExperiment", "name": "piControl", "ontologyTypeKey": "cim.2.shared.DocReference"}, {"id": "479ff5ed-9c56-4d1e-98c3-f97a0864e7b4", "version": 1, "type": "cim.2.designing.NumericalExperiment", "name": "historical", "ontologyTypeKey": "cim.2.shared.DocReference"}, {"id": "0d399294-4ced-4f4b-bfdc-ece79d1f00f0", "version": 1, "type": "cim.2.designing.NumericalExperiment", "name": "forecast-Pinatubo", "ontologyTypeKey": "cim.2.shared.DocReference"}], "ontologyTypeKey": "cim.2.designing.NumericalExperiment", "internalName": "VolMIP1.2", "canonicalName": "volcEq-full", "meta": {"language": "en", "author": {"version": 1, "uid": "253825f3-fbc8-43fb-b1f6-cc575dc693eb", "ontologyTypeKey": "cim.2.shared.DocReference"}, "institute": "--", "createDate": "2016-07-01 15:14:57.593616", "subProjects": ["VolMIP"], "project": "cmip6-draft", "source": "spreadsheet", "version": 1, "updateDate": "2016-07-01 15:14:57.593616", "ontologyTypeKey": "cim.2.shared.DocMetaInfo", "type": "cim.2.designing.NumericalExperiment", "id": "4a9c0aee-c0ac-454d-9c14-0c17f2e37576"}, "references": [{"version": 1, "type": "cim.2.shared.Citation", "id": "9e139643-3060-4b5b-9869-269f6d66c19b", "ontologyTypeKey": "cim.2.shared.DocReference"}, {"version": 1, "type": "cim.2.shared.Citation", "id": "ab7ed4bd-b97f-43be-8a9e-4e053d33e050", "ontologyTypeKey": "cim.2.shared.DocReference"}, {"version": 1, "type": "cim.2.shared.Citation", "id": "0d337e18-6df7-46df-be20-d54eb8f5716e", "ontologyTypeKey": "cim.2.shared.DocReference"}], "rationale": "To investigate the uncertainty in the climate response to strong volcanic eruptions with focus on short-term response. To investigate the robustess of volcanic imprint on the Northern Hemisphere winter climate and of associated dynamics.  A large ensemble is required to accurately estimate simulated responses to volcanic forcing which may be comparable to the amplitude of internal interannual variability.", "longName": "Pinatubo experiment with full volcanic forcing", "keywords": "VolMIP, Tier 1, Pinatubo, volcano, volcanic forcing, eruption", "alternativeNames": ["VolShort20EQfull"], "name": "volcEq-full"}