{"citationDetail": "Matthes K., B. Funke, M. E. Anderson, L. Barnard, J. Beer, P. Charbonneau, M. A. Clilverd, T. Dudok de Wit, M. Haberreiter, A. Hendry, C. H. Jackman, M. Kretzschmar, T. Kruschke, M. Kunze, U. Langematz, A. Maycock, S. Misios, C. J. Rodger, A. A. Scaife, A. Seppa\u0308la\u0308, M. Shangguan, M. Sinnhuber, K. Tourpali, I. Usoskin, M. von der Kamp, P. T. Verronen, S. Versick: Solar Forcing for CMIP6, Geosci. Model Dev., to be submitted", "title": "Solar Forcing for CMIP6", "abstract": "The future solar forcing data recommended for CMIP6 has a downward trend.", "meta": {"language": "en", "author": {"version": 1, "uid": "253825f3-fbc8-43fb-b1f6-cc575dc693eb", "ontologyTypeKey": "cim.2.shared.DocReference"}, "institute": "--", "createDate": "2016-07-04 13:00:00", "project": "cmip6-draft", "source": "spreadsheet", "version": 1, "updateDate": "2016-07-04 13:00:00", "ontologyTypeKey": "cim.2.shared.DocMetaInfo", "type": "cim.2.shared.Citation", "id": "729b5e0c-ac7c-41bb-a804-54c2ef02dcf7"}, "context": "The future solar forcing data recommended for CMIP6 has a downward trend.", "ontologyTypeKey": "cim.2.shared.Citation"}