{"additionalRequirements": [{"id": "7b9cd8ae-10f1-4630-93be-0f93e508b478", "version": 1, "type": "cim.2.designing.ForcingConstraint", "name": "PreIndustrialWMGHGConcentrationsNoCO2", "ontologyTypeKey": "cim.2.shared.DocReference"}, {"id": "36b8469f-b8e0-4a9a-bae6-6aadb1552d88", "version": 1, "type": "cim.2.designing.ForcingConstraint", "name": "PreIndustrialCO2", "ontologyTypeKey": "cim.2.shared.DocReference"}, {"id": "ae5ca3af-1db8-4d51-ab95-4b1bc5d6c81e", "version": 1, "type": "cim.2.designing.ForcingConstraint", "name": "Pre-IndustrialAerosol", "ontologyTypeKey": "cim.2.shared.DocReference"}, {"id": "14472206-0367-41d8-9fd5-20d30945c60c", "version": 1, "type": "cim.2.designing.ForcingConstraint", "name": "Pre-IndustrialArePre", "ontologyTypeKey": "cim.2.shared.DocReference"}, {"id": "ffb0a978-eafe-4e4a-a0dc-f1204a26f2ae", "version": 1, "type": "cim.2.designing.ForcingConstraint", "name": "Pre-IndustrialStratosphericH2OConcentrations", "ontologyTypeKey": "cim.2.shared.DocReference"}, {"id": "31852cd6-8975-4e6a-944f-9dd53e507ff7", "version": 1, "type": "cim.2.designing.ForcingConstraint", "name": "Pre-industrialStratosphericAerosol", "ontologyTypeKey": "cim.2.shared.DocReference"}, {"id": "31852cd6-8975-4e6a-944f-9dd53e507ff7", "version": 1, "type": "cim.2.designing.ForcingConstraint", "name": "Pre-industrialStratosphericAerosol", "ontologyTypeKey": "cim.2.shared.DocReference"}, {"id": "9362a0d5-041d-424a-8d56-b4fcbaac0b1d", "version": 1, "type": "cim.2.designing.ForcingConstraint", "name": "Pre-IndustrialSolar", "ontologyTypeKey": "cim.2.shared.DocReference"}], "ontologyTypeKey": "cim.2.designing.NumericalRequirement", "canonicalName": "piForcingExcludingLandUse", "name": "PIForcingExcludingLandUse", "citations": [{"version": 1, "type": "cim.2.shared.Citation", "id": "9e139643-3060-4b5b-9869-269f6d66c19b", "ontologyTypeKey": "cim.2.shared.DocReference"}], "meta": {"language": "en", "author": {"version": 1, "uid": "253825f3-fbc8-43fb-b1f6-cc575dc693eb", "ontologyTypeKey": "cim.2.shared.DocReference"}, "institute": "--", "createDate": "2016-07-04 13:00:00", "project": "cmip6-draft", "source": "spreadsheet", "version": 1, "updateDate": "2016-07-04 13:00:00", "ontologyTypeKey": "cim.2.shared.DocMetaInfo", "type": "cim.2.designing.NumericalRequirement", "id": "62825565-3d5f-47e1-a549-bbe7308c8979"}, "longName": "Pre-Industrial forcing, excluding land-use", "keywords": "pre-industrial forcing, excluding land-use", "isConformanceRequested": true, "description": "Pre-Industrial forcing excluding land-use."}