{"internalName": "CFMIP2.5.02", "requirements": [{"id": "b3abe55c-0802-4327-9c13-129773d94916", "version": 1, "type": "cim.2.designing.TemporalConstraint", "name": "30yrs1960-1989", "ontologyTypeKey": "cim.2.shared.DocReference"}, {"id": "af9ec5c1-9e65-4b92-8133-8da0a1ba828d", "version": 1, "type": "cim.2.designing.ForcingConstraint", "name": "piControlSSTMnthlyVarPlusUniform4K", "ontologyTypeKey": "cim.2.shared.DocReference"}, {"id": "560d5187-2f24-4882-a964-9fc9a6e8d129", "version": 1, "type": "cim.2.designing.ForcingConstraint", "name": "piControlSICMnthlyVar", "ontologyTypeKey": "cim.2.shared.DocReference"}, {"id": "36b8469f-b8e0-4a9a-bae6-6aadb1552d88", "version": 1, "type": "cim.2.designing.ForcingConstraint", "name": "PreIndustrialCO2", "ontologyTypeKey": "cim.2.shared.DocReference"}, {"id": "834c34fd-9f2d-49c4-80cd-50fb98852d14", "version": 1, "type": "cim.2.designing.NumericalRequirement:forcing_constraint", "name": "piForcingExcludingCO2", "ontologyTypeKey": "cim.2.shared.DocReference"}, {"id": "1ef19c06-f6fb-4836-907f-ad4749162091", "version": 1, "type": "cim.2.designing.EnsembleRequirement", "name": "SingleMemberEnsemble", "ontologyTypeKey": "cim.2.shared.DocReference"}, {"id": "54937ca0-e3f0-4882-85c6-43fb02647491", "version": 1, "type": "cim.2.designing.NumericalRequirement:model_configuration", "name": "AGCMConfiguration", "ontologyTypeKey": "cim.2.shared.DocReference"}], "description": "An AGCM experiment with monthly-varying SSTs and sea-ice taken from each model's own piControl simulation (using the 30 years of piControl that are parallel to years 111-140 of its abrupt4xCO2 run) but with a uniform SST increase of 4K. Dynamic vegetation should be turned off.\nSame as sstPi but with SSTs uniformly increased by 4K.", "ontologyTypeKey": "cim.2.designing.NumericalExperiment", "relatedExperiments": [{"id": "7dd72de5-c5b6-412c-9b4c-540f09538d9a", "version": 1, "type": "cim.2.designing.NumericalExperiment", "name": "piControl", "ontologyTypeKey": "cim.2.shared.DocReference"}, {"id": "26ff4dc9-6c52-45e3-8c42-0afc828cc787", "version": 1, "type": "cim.2.designing.NumericalExperiment", "name": "piSST-control", "ontologyTypeKey": "cim.2.shared.DocReference"}], "parties": [{"party": ["point of contact:", "Rob Chadwick", "Herv\u00e9 Douville"], "ontologyTypeKey": "cim.2.shared.Responsibility"}], "canonicalName": "piSST-p4K", "citations": [{"version": 1, "type": "cim.2.shared.Citation", "id": "9e139643-3060-4b5b-9869-269f6d66c19b", "ontologyTypeKey": "cim.2.shared.DocReference"}, {"version": 1, "type": "cim.2.shared.Citation", "id": "10860584-06ea-4417-ae1a-811ef9415dd9", "ontologyTypeKey": "cim.2.shared.DocReference"}], "meta": {"language": "en", "author": {"version": 1, "uid": "253825f3-fbc8-43fb-b1f6-cc575dc693eb", "ontologyTypeKey": "cim.2.shared.DocReference"}, "institute": "--", "createDate": "2016-07-04 13:00:00", "project": "cmip6-draft", "source": "spreadsheet", "version": 1, "updateDate": "2016-07-04 13:00:00", "ontologyTypeKey": "cim.2.shared.DocMetaInfo", "type": "cim.2.designing.NumericalExperiment", "id": "2326d4cc-58cd-4e6d-8130-08a9a2eabf9b"}, "rationale": "To understand regional climate responses to CO2 forcing.", "longName": "control plus 4K SSTs", "keywords": "CFMIP, Tier 2, Pre-industrial SST plus 4K, PI forcing", "alternativeNames": ["sstPi4K"], "name": "piSST-p4K"}