{"description": 3.0, "parties": [{"meta": {"type": "cim.2.shared.Responsibility"}, "parties": ["point of contact:", "Bart van den Hurk"]}], "canonicalName": "LFMIP-CAForcing", "name": "LFMIP-CAForcing", "citations": [{"meta": {"type": "cim.2.shared.DocReference"}, "type": "cim.2.shared.Citation", "version": 1, "id": "9e139643-3060-4b5b-9869-269f6d66c19b"}], "meta": {"author": {"version": 1, "meta": {"type": "cim.2.shared.DocReference"}, "uid": "253825f3-fbc8-43fb-b1f6-cc575dc693eb"}, "createDate": "2016-07-04 13:00:00", "project": "cmip6-draft", "source": "spreadsheet", "version": 1, "updateDate": "2016-07-04 13:00:00", "type": "cim.2.designing.ForcingConstraint", "id": "1a9f8a1c-bd4a-414d-aef4-c09891ef4d35"}, "rationale": "LFMIP, present climate, land surface forcing", "longName": "Present climate land surface forcing", "keywords": 1.0, "isConformanceRequested": false}