{"responsibleParties": [{"party": [{"id": "df9b43fd-33e4-43b5-8be9-846f59ee3c12", "version": 1, "type": "cim.2.shared.Party", "name": "George Hurtt", "ontologyTypeKey": "cim.2.shared.DocReference"}, {"id": "161b222a-3e2a-4820-8f76-c7accad4ca2b", "version": 1, "type": "cim.2.shared.Party", "name": "David Lawrence", "ontologyTypeKey": "cim.2.shared.DocReference"}], "ontologyTypeKey": "cim.2.shared.Responsibility"}], "requirements": [{"id": "9c6226cd-c82c-4410-bf2e-421bf3820e11", "version": 1, "type": "cim.2.designing.TemporalConstraint", "name": "165yrs1850-2014", "ontologyTypeKey": "cim.2.shared.DocReference"}, {"id": "aae0d3f5-a6c7-4edc-883d-ca65b29f6f02", "version": 1, "type": "cim.2.designing.ForcingConstraint", "name": "PreIndustrialLandUse", "ontologyTypeKey": "cim.2.shared.DocReference"}, {"id": "c46e9e36-0501-4a90-9179-ba0aaea007ba", "version": 1, "type": "cim.2.designing.ForcingConstraint", "name": "PreIndustrialLandCover", "ontologyTypeKey": "cim.2.shared.DocReference"}, {"id": "b4810817-5b10-4e8a-89bf-696b6f888e99", "version": 1, "type": "cim.2.designing.ForcingConstraint", "name": "HistoricalWMGHGConcentrations", "ontologyTypeKey": "cim.2.shared.DocReference"}, {"id": "cb2b616a-fe82-4c1a-8ee3-e0390909fe48", "version": 1, "type": "cim.2.designing.ForcingConstraint", "name": "HistoricalStratosphericAerosol", "ontologyTypeKey": "cim.2.shared.DocReference"}, {"id": "3a2e7bd4-a0dd-4d10-bebd-1eb6b4c6e906", "version": 1, "type": "cim.2.designing.NumericalRequirement:forcing_constraint", "name": "HistoricalAerosolForcing", "ontologyTypeKey": "cim.2.shared.DocReference"}, {"id": "b7d6de28-2238-45af-b199-2b2f68ae4437", "version": 1, "type": "cim.2.designing.NumericalRequirement:forcing_constraint", "name": "HistoricalSolarForcing", "ontologyTypeKey": "cim.2.shared.DocReference"}, {"id": "b19b46f8-6355-40ef-9ca8-9a4e8b630ab1", "version": 1, "type": "cim.2.designing.NumericalRequirement:forcing_constraint", "name": "HistoricalO3andStratosphericH2OConcentrations", "ontologyTypeKey": "cim.2.shared.DocReference"}, {"id": "02bb3aad-3224-4535-9bfe-29d4856cb0ba", "version": 1, "type": "cim.2.designing.EnsembleRequirement", "name": "MinimumOneMemberEnsemble", "ontologyTypeKey": "cim.2.shared.DocReference"}, {"id": "4cf855cf-777b-4af7-aa47-9fe7466cfce3", "version": 1, "type": "cim.2.designing.NumericalRequirement:model_configuration", "name": "AOGCM/ESMConfiguration", "ontologyTypeKey": "cim.2.shared.DocReference"}], "description": "Concentration driven historical forcing with land use held constant at 1850 usage. No human activity.", "ontologyTypeKey": "cim.2.designing.NumericalExperiment", "relatedExperiments": [{"id": "7dd72de5-c5b6-412c-9b4c-540f09538d9a", "version": 1, "type": "cim.2.designing.NumericalExperiment", "name": "piControl", "ontologyTypeKey": "cim.2.shared.DocReference"}, {"id": "479ff5ed-9c56-4d1e-98c3-f97a0864e7b4", "version": 1, "type": "cim.2.designing.NumericalExperiment", "name": "historical", "ontologyTypeKey": "cim.2.shared.DocReference"}, {"id": "ab949b54-d56e-48e7-9657-44262d51c2fb", "version": 1, "type": "cim.2.designing.NumericalExperiment", "name": "land-hist", "ontologyTypeKey": "cim.2.shared.DocReference"}], "relatedMips": [{"id": "ec9243df-26b7-4ed5-ba77-beb65bc13276", "version": 1, "type": "cim.2.designing.Project", "name": "lumip", "ontologyTypeKey": "cim.2.shared.DocReference"}], "internalName": "LUMIP1.6", "canonicalName": "hist-noLu", "meta": {"language": "en", "author": {"version": 1, "uid": "253825f3-fbc8-43fb-b1f6-cc575dc693eb", "ontologyTypeKey": "cim.2.shared.DocReference"}, "institute": "--", "createDate": "2016-07-04 13:00:00", "subProjects": ["LUMIP"], "project": "cmip6-draft", "source": "spreadsheet", "version": 1, "updateDate": "2016-07-04 13:00:00", "ontologyTypeKey": "cim.2.shared.DocMetaInfo", "type": "cim.2.designing.NumericalExperiment", "id": "90eb5274-c9d4-472f-b3da-30b2595193a0"}, "references": [{"version": 1, "type": "cim.2.shared.Citation", "id": "9e139643-3060-4b5b-9869-269f6d66c19b", "ontologyTypeKey": "cim.2.shared.DocReference"}, {"version": 1, "type": "cim.2.shared.Citation", "id": "41629317-f948-434f-815b-781f430a8bf9", "ontologyTypeKey": "cim.2.shared.DocReference"}], "rationale": "Land-use change impact on past climate", "longName": "historical with no land-use change", "keywords": "LUMIP, Tier 1, Historical, pre-industrial Land Use and Land Cover, 1850", "alternativeNames": ["noLULCC_hist", "HistNolulcc01"], "name": "hist-noLu"}