{"internalName": "PMIP1.5", "requirements": [{"id": "7af98410-3122-4783-b421-d9e38bd31b3b", "version": 1, "type": "cim.2.designing.TemporalConstraint", "name": "100yrsAfterSpinUp", "ontologyTypeKey": "cim.2.shared.DocReference"}, {"id": "f68f06f6-dd53-440e-aa06-a9ffd36f8298", "version": 1, "type": "cim.2.designing.ForcingConstraint", "name": "midPlioCO2", "ontologyTypeKey": "cim.2.shared.DocReference"}, {"id": "d8b67f96-2edf-423f-88d2-81471542500f", "version": 1, "type": "cim.2.designing.ForcingConstraint", "name": "midPlioAstroParams", "ontologyTypeKey": "cim.2.shared.DocReference"}, {"id": "2c94b362-e6b9-4679-96ed-c19784fdb741", "version": 1, "type": "cim.2.designing.ForcingConstraint", "name": "midPlioIceSheet", "ontologyTypeKey": "cim.2.shared.DocReference"}, {"id": "1f66cb1b-8a5a-4b8f-9a14-121f5645c401", "version": 1, "type": "cim.2.designing.ForcingConstraint", "name": "midPlioLandSeaMask", "ontologyTypeKey": "cim.2.shared.DocReference"}, {"id": "158930c3-0dde-40f0-b8cb-0202a8713239", "version": 1, "type": "cim.2.designing.ForcingConstraint", "name": "midPlioTopog", "ontologyTypeKey": "cim.2.shared.DocReference"}, {"id": "1ef19c06-f6fb-4836-907f-ad4749162091", "version": 1, "type": "cim.2.designing.EnsembleRequirement", "name": "SingleMemberEnsemble", "ontologyTypeKey": "cim.2.shared.DocReference"}, {"id": "44d8cb89-0252-45e0-a7c7-8d108e2b6dc8", "version": 1, "type": "cim.2.designing.NumericalRequirement:model_configuration", "name": "AOGCMconfiguration", "ontologyTypeKey": "cim.2.shared.DocReference"}], "description": "Impose Mid-Pliocene Warm Period (3.2 Ma ago) boundary conditions for ice sheet and land-sea mask, topography (smaller ice sheets),  the atmospheric concentration of well-mixed greenhouse gases and orbital parameters.  Run for at least 100 years after spin-up. It is mandatory that the model versions used for the PMIP-CMIP6 experiments are the exactly the same as for the other CMIP6 experiments, in particular the DECK and historical simulations.", "ontologyTypeKey": "cim.2.designing.NumericalExperiment", "relatedExperiments": [{"id": "7dd72de5-c5b6-412c-9b4c-540f09538d9a", "version": 1, "type": "cim.2.designing.NumericalExperiment", "name": "piControl", "ontologyTypeKey": "cim.2.shared.DocReference"}], "relatedMips": [{"id": "2cf0d709-28b9-4dbd-a323-713e273851f7", "version": 1, "type": "cim.2.designing.Project", "name": "pmip", "ontologyTypeKey": "cim.2.shared.DocReference"}], "canonicalName": "midPliocene-eoi400", "parties": [{"party": ["point of contact:", "Pascale Braconnot", "Sandy Harrison"], "ontologyTypeKey": "cim.2.shared.Responsibility"}], "citations": [{"version": 1, "type": "cim.2.shared.Citation", "id": "9e139643-3060-4b5b-9869-269f6d66c19b", "ontologyTypeKey": "cim.2.shared.DocReference"}, {"version": 1, "type": "cim.2.shared.Citation", "id": "c209680b-4f1e-4fc4-af6d-f47805e0b322", "ontologyTypeKey": "cim.2.shared.DocReference"}, {"version": 1, "type": "cim.2.shared.Citation", "id": "284318c8-08eb-4a7e-a544-175f253bbe35", "ontologyTypeKey": "cim.2.shared.DocReference"}], "meta": {"language": "en", "author": {"version": 1, "uid": "253825f3-fbc8-43fb-b1f6-cc575dc693eb", "ontologyTypeKey": "cim.2.shared.DocReference"}, "institute": "--", "createDate": "2016-07-04 13:00:00", "subProjects": ["PMIP"], "project": "cmip6-draft", "source": "spreadsheet", "version": 1, "updateDate": "2016-07-04 13:00:00", "ontologyTypeKey": "cim.2.shared.DocMetaInfo", "type": "cim.2.designing.NumericalExperiment", "id": "5ab9737e-a264-4378-a8b2-f0658832b583"}, "rationale": "How does the Earth System respond in the long term to CO2 forcing analogous to that of the modern?  What is the significance of CO2 induced polar amplification for the stability of the ice sheets, sea-ice and sea-level?", "longName": "mid-Pliocene warm period", "keywords": "PMIP, Tier 1, PlioExp, Pliiocene warm, 3.2 Ma", "alternativeNames": ["PlioExp"], "name": "midPliocene-eoi400"}