{
    "MIP_ERA": "cmip6", 
    "INSTITUTE": "ipsl", 
    "SOURCE_ID": "ipsl-cm6a-lr", 
    "REALM": "seaice", 
    "AUTHORS": [
        {
            "name": "Mark A. Greenslade", 
            "email": "momipsl@ipsl.jussieu.fr"
        }, 
        {
            "name": "Mark G. Greenslade", 
            "email": "mxmipsl@ipsl.jussieu.fr"
        }
    ], 
    "CONTRIBUTORS": [
        {
            "name": "Mark A. Greenslade", 
            "email": "momipsl@ipsl.jussieu.fr"
        }
    ], 
    "CONTENT": {
        "cmip6.seaice.key_properties.variables.prognostic": {
            "qc_status": 0, 
            "values": [
                "Sea ice Temperature"
            ]
        }
    }
}