{
    "gfdl-am4": {
        "aerosol": "cmip5:gfdl-cm3", 
        "atmos": "cmip5:gfdl-cm3", 
        "atmoschem": "cmip5:gfdl-cm3", 
        "land": "cmip5:gfdl-cm3", 
        "landice": "cmip5:gfdl-cm3", 
        "ocean": "", 
        "ocnbgchem": "", 
        "seaice": ""
    }, 
    "gfdl-cm4": {
        "aerosol": "cmip6:gfdl-am4", 
        "atmos": "cmip6:gfdl-am4", 
        "atmoschem": "cmip6:gfdl-am4", 
        "land": "cmip6:gfdl-am4", 
        "landice": "cmip6:gfdl-am4", 
        "ocean": "cmip5:gfdl-cm3", 
        "ocnbgchem": "", 
        "seaice": "cmip5:gfdl-cm3"
    }, 
    "gfdl-esm4": {
        "aerosol": "cmip6:gfdl-cm4", 
        "atmos": "cmip6:gfdl-cm4", 
        "atmoschem": "cmip6:gfdl-cm4", 
        "land": "cmip6:gfdl-cm4", 
        "landice": "cmip6:gfdl-cm4", 
        "ocean": "cmip6:gfdl-cm4", 
        "ocnbgchem": "cmip5:gfdl-esm2m", 
        "seaice": "cmip6:gfdl-cm4"
    }
}
